miniwdl_s3parcp.py
miniwdl_s3parcp-0.0.5.dist-info/LICENSE
miniwdl_s3parcp-0.0.5.dist-info/METADATA
miniwdl_s3parcp-0.0.5.dist-info/WHEEL
miniwdl_s3parcp-0.0.5.dist-info/entry_points.txt
miniwdl_s3parcp-0.0.5.dist-info/top_level.txt
miniwdl_s3parcp-0.0.5.dist-info/RECORD
