Metadata-Version: 2.1
Name: miniwdl-s3parcp
Version: 0.0.5
Summary: miniwdl download plugin for s3:// using s3parcp
Home-page: https://github.com/chanzuckerberg/miniwdl-s3parcp
Author: Mike Lin, Andrey Kislyuk
License: UNKNOWN
Project-URL: Documentation, https://github.com/chanzuckerberg/miniwdl-s3parcp
Project-URL: Source Code, https://github.com/chanzuckerberg/miniwdl-s3parcp
Project-URL: Issue Tracker, https://github.com/chanzuckerberg/miniwdl-s3parcp/issues
Platform: UNKNOWN
Requires-Python: >=3.6
Requires-Dist: boto3
